MANIFEST.in
README.rst
setup.cfg
setup.py
django_email_integration_test/VERSION
django_email_integration_test/__init__.py
django_email_integration_test.egg-info/PKG-INFO
django_email_integration_test.egg-info/SOURCES.txt
django_email_integration_test.egg-info/dependency_links.txt
django_email_integration_test.egg-info/requires.txt
django_email_integration_test.egg-info/top_level.txt
django_email_integration_test/management/__init__.py
django_email_integration_test/management/commands/__init__.py
django_email_integration_test/management/commands/email_integration_test.py