Metadata-Version: 1.1
Name: django-email-integration-test
Version: 0.1.0
Summary: Email integration test for Django.
Home-page: https://github.com/lddubeau/django-email-integration-test
Author: Louis-Dominique Dubeau
Author-email: ldd@lddubeau.com
License: MPL 2.0
Keywords: Django,testing,email
Platform: UNKNOWN
Classifier: Programming Language :: Python
Classifier: Programming Language :: Python :: 3
Classifier: Programming Language :: Python :: 3 :: Only
Classifier: Programming Language :: Python :: 3.6
Classifier: Programming Language :: Python :: 3.7
Classifier: Development Status :: 4 - Beta
Classifier: Intended Audience :: Developers
Classifier: License :: OSI Approved :: Mozilla Public License 2.0 (MPL 2.0)
Classifier: Operating System :: POSIX
Classifier: Framework :: Django
Classifier: Framework :: Django :: 2.2
Classifier: Topic :: Software Development :: Libraries
Classifier: Topic :: Utilities
